tasker/__init__.py
tasker/__main__.py
tasker/_version.py
tasker/decorator.py
tasker/launcher.py
tasker/mixin.py
tasker/typedef.py
tasker/utils.py
tasker/contrib/__init__.py
tasker/contrib/torch.py
tasker/storages/__init__.py
tasker/storages/basic.py
tasker/storages/pickle.py
tasker/tasks/__init__.py
tasker/tasks/containers.py
tasker/tasks/utils.py
waterch/__init__.py
waterch_tasker-0.4.3.dist-info/LICENSE
waterch_tasker-0.4.3.dist-info/METADATA
waterch_tasker-0.4.3.dist-info/WHEEL
waterch_tasker-0.4.3.dist-info/entry_points.txt
waterch_tasker-0.4.3.dist-info/top_level.txt
waterch_tasker-0.4.3.dist-info/RECORD
