Metadata-Version: 2.1
Name: waterch-tasker
Version: 0.4.3
Summary: A scalable and extendable experiment task scheduler framework.
Home-page: https://github.com/chenrz925/waterch-tasker
Author: Chen Runze
Author-email: chenrz925@icloud.com
License: UNKNOWN
Project-URL: Documentation, https://waterch-tasker.readthedocs.io/en/latest/
Project-URL: Source Code, https://github.com/chenrz925/waterch-tasker
Platform: UNKNOWN
Classifier: Development Status :: 1 - Planning
Classifier: License :: OSI Approved :: Apache Software License
Classifier: Programming Language :: Python :: 3
Requires-Dist: python-box (>=4.2.3)
Requires-Dist: toml (>=0.10.1)
Requires-Dist: more-itertools (>=8.3.0)
Provides-Extra: pytorch
Requires-Dist: torch (>=1.7.1) ; extra == 'pytorch'
Requires-Dist: pytorch-ignite (>=0.4.3) ; extra == 'pytorch'
